tests/__init__.py
tests/test_configuration.py
yaml_config_wrapper/__init__.py
yaml_config_wrapper/configuration.py
yaml_config_wrapper/default_schema.json
yaml_config_wrapper-1.0.4.data/data/default_schema.json
yaml_config_wrapper-1.0.4.dist-info/LICENSE
yaml_config_wrapper-1.0.4.dist-info/METADATA
yaml_config_wrapper-1.0.4.dist-info/WHEEL
yaml_config_wrapper-1.0.4.dist-info/entry_points.txt
yaml_config_wrapper-1.0.4.dist-info/top_level.txt
yaml_config_wrapper-1.0.4.dist-info/RECORD
