Metadata-Version: 2.1
Name: yaml-config-wrapper
Version: 1.0.4
Summary: A YAML configuration wrapper.
Home-page: https://github.com/drkostas/yaml-config-wrapper/tree/master/
Author: Kostas Georgiou
Author-email: georgiou.kostas94@gmail.com
License: Apache Software License 2.0
Keywords: yaml,yml,config,configuration,wrapper
Platform: UNKNOWN
Classifier: Development Status :: 5 - Production/Stable
Classifier: Intended Audience :: Developers
Classifier: License :: OSI Approved :: Apache Software License
Classifier: Natural Language :: English
Classifier: Programming Language :: Python :: 3.6
Classifier: Programming Language :: Python :: 3.7
Classifier: Programming Language :: Python :: 3.8
Requires-Python: >=3.6
License-File: LICENSE
Requires-Dist: jsonschema
Requires-Dist: PyYAML
